tuyalinksdk/__init__.py
tuyalinksdk/atop.py
tuyalinksdk/client.py
tuyalinksdk/console_qrcode.py
tuyalinksdk/iotdns.py
tuyalinksdk/mqtt_bind.py
tuyalinksdk/mqtt_builder.py
tuyalinksdk-0.0.3.dist-info/LICENSE
tuyalinksdk-0.0.3.dist-info/METADATA
tuyalinksdk-0.0.3.dist-info/WHEEL
tuyalinksdk-0.0.3.dist-info/top_level.txt
tuyalinksdk-0.0.3.dist-info/RECORD
