Metadata-Version: 2.1
Name: tuyalinksdk
Version: 0.0.3
Summary: TuyaOS Link SDK for Python
Home-page: https://github.com/tuya/tuyaos-link-sdk-python.git
Author: Tuya SDK Common Runtime Team
License: License :: OSI Approved :: MIT License
Platform: UNKNOWN
Classifier: Programming Language :: Python :: 3
Classifier: License :: OSI Approved :: MIT License
Classifier: Operating System :: OS Independent
Requires-Python: >=3.6
